pyrolite_meltsutil/__init__.py
pyrolite_meltsutil/_version.py
pyrolite_meltsutil/download.py
pyrolite_meltsutil/env.py
pyrolite_meltsutil/meltsfile.py
pyrolite_meltsutil/parse.py
pyrolite_meltsutil/web.py
pyrolite_meltsutil/automation/__init__.py
pyrolite_meltsutil/automation/naming.py
pyrolite_meltsutil/automation/org.py
pyrolite_meltsutil/automation/process.py
pyrolite_meltsutil/automation/timing.py
pyrolite_meltsutil/data/__init__.py
pyrolite_meltsutil/data/__pycache__/__init__.cpython-36-pytest-5.1.3.pyc
pyrolite_meltsutil/data/__pycache__/__init__.cpython-36.pyc
pyrolite_meltsutil/data/__pycache__/__init__.cpython-37-pytest-5.0.0.pyc
pyrolite_meltsutil/data/__pycache__/__init__.cpython-37-pytest-5.2.1.pyc
pyrolite_meltsutil/data/__pycache__/__init__.cpython-37.pyc
pyrolite_meltsutil/data/__pycache__/env.cpython-36-pytest-5.1.3.pyc
pyrolite_meltsutil/data/__pycache__/env.cpython-36.pyc
pyrolite_meltsutil/data/__pycache__/env.cpython-37-pytest-5.0.0.pyc
pyrolite_meltsutil/data/data_examples/batch/autolog.log
pyrolite_meltsutil/data/data_examples/batch/meltsBatchConfig.json
pyrolite_meltsutil/data/data_examples/batch/phases.csv
pyrolite_meltsutil/data/data_examples/batch/system.csv
pyrolite_meltsutil/data/data_examples/batch/363f3d0a0b/Bulk_comp_tbl.txt
pyrolite_meltsutil/data/data_examples/batch/363f3d0a0b/Gale2013MORBisobarfrac5-5kbar1300-800CFMQ363f3d0a0b.melts
pyrolite_meltsutil/data/data_examples/batch/363f3d0a0b/Gale2013MORBisobarfrac5-5kbar1300-800CFMQ363f3d0a0b.melts_bak
pyrolite_meltsutil/data/data_examples/batch/363f3d0a0b/Liquid_comp_tbl.txt
pyrolite_meltsutil/data/data_examples/batch/363f3d0a0b/Phase_main_tbl.txt
pyrolite_meltsutil/data/data_examples/batch/363f3d0a0b/Phase_mass_tbl.txt
pyrolite_meltsutil/data/data_examples/batch/363f3d0a0b/Phase_vol_tbl.txt
pyrolite_meltsutil/data/data_examples/batch/363f3d0a0b/Solid_comp_tbl.txt
pyrolite_meltsutil/data/data_examples/batch/363f3d0a0b/System_main_tbl.txt
pyrolite_meltsutil-0.1.6.dist-info/LICENSE
pyrolite_meltsutil-0.1.6.dist-info/METADATA
pyrolite_meltsutil-0.1.6.dist-info/WHEEL
pyrolite_meltsutil-0.1.6.dist-info/top_level.txt
pyrolite_meltsutil-0.1.6.dist-info/RECORD
