Metadata-Version: 2.1
Name: pyrolite-meltsutil
Version: 0.1.6
Summary: pyrolite extension for working with alphaMELTS and its outputs.
Home-page: https://github.com/morganjwilliams/pyrolite-meltsutil
Author: Morgan Williams
Author-email: morgan.williams@csiro.au
License: CSIRO Modifed MIT/BSD
Project-URL: Documentation, https://pyrolite-meltsutil.readthedocs.com/
Project-URL: Code, https://github.com/morganjwilliams/pyrolite-meltsutil
Project-URL: Issue tracker, https://github.com/morganjwilliams/pyrolite-meltsutil/issues
Keywords: geochemistry,compositional data,visualisation,petrology
Platform: UNKNOWN
Classifier: Development Status :: 2 - Pre-Alpha
Classifier: Intended Audience :: Science/Research
Classifier: Natural Language :: English
Classifier: Programming Language :: Python :: 3 :: Only
Classifier: Programming Language :: Python :: 3.6
Classifier: Programming Language :: Python :: 3.7
Classifier: Programming Language :: Python :: 3.8
Classifier: Topic :: Scientific/Engineering
Classifier: Topic :: Software Development :: Libraries :: Python Modules
Requires-Dist: pyrolite (>=0.2.7)
Requires-Dist: requests
Requires-Dist: psutil
Requires-Dist: xmljson
Requires-Dist: dicttoxml
Requires-Dist: tqdm
Provides-Extra: dev
Requires-Dist: pytest ; extra == 'dev'
Requires-Dist: versioneer ; extra == 'dev'
Requires-Dist: black ; extra == 'dev'
Requires-Dist: twine ; extra == 'dev'
Requires-Dist: sphinx-rtd-theme ; extra == 'dev'
Requires-Dist: sphinx-autodoc-annotation ; extra == 'dev'
Requires-Dist: sphinx-gallery (>=0.6.0) ; extra == 'dev'
Requires-Dist: recommonmark ; extra == 'dev'
Requires-Dist: pytest-runner ; extra == 'dev'
Requires-Dist: pytest-cov ; extra == 'dev'
Requires-Dist: coverage ; extra == 'dev'
Requires-Dist: coveralls ; extra == 'dev'
